rakam_eval_sdk/__init__.py
rakam_eval_sdk/cli.py
rakam_eval_sdk/client.py
rakam_eval_sdk/decorators.py
rakam_eval_sdk/schema.py
rakam_eval_sdk/utils/decorator_utils.py
rakam_eval_sdk-0.2.3.dist-info/WHEEL
rakam_eval_sdk-0.2.3.dist-info/entry_points.txt
rakam_eval_sdk-0.2.3.dist-info/METADATA
rakam_eval_sdk-0.2.3.dist-info/RECORD
