Metadata-Version: 2.3
Name: rakam-eval-sdk
Version: 0.2.3
Summary: Evaluation Framework SDK
Author: Mohamed Bachar Touil
License: MIT
Requires-Dist: dotenv>=0.9.9
Requires-Dist: psutil>=7.2.1
Requires-Dist: pydantic>=2.10.6
Requires-Dist: requests
Requires-Dist: typer>=0.20.1
Requires-Python: >=3.8
